ci/configuration_server.py
fiduswriter/pandoc/__init__.py
fiduswriter/pandoc/apps.py
fiduswriter/pandoc/package.json5
fiduswriter/pandoc/static/js/modules/pandoc/app.js
fiduswriter/pandoc/static/js/modules/pandoc/constants.js
fiduswriter/pandoc/static/js/modules/pandoc/editor.js
fiduswriter/pandoc/static/js/modules/pandoc/exporter.js
fiduswriter/pandoc/static/js/modules/pandoc/helpers.js
fiduswriter/pandoc/static/js/modules/pandoc/importer.js
fiduswriter/pandoc/static/js/plugins/app/pandoc.js
fiduswriter/pandoc/static/js/plugins/editor/pandoc.js
fiduswriter/pandoc/tests/__init__.py
fiduswriter/pandoc/tests/test_pandoc.py
fiduswriter/pandoc_on_server/__init__.py
fiduswriter/pandoc_on_server/apps.py
fiduswriter/pandoc_on_server/urls.py
fiduswriter/pandoc_on_server/views.py
fiduswriter/pandoc_on_server/tests/__init__.py
fiduswriter/pandoc_on_server/tests/test_pandoc.py
fiduswriter_pandoc-4.0.3.dist-info/licenses/LICENSE
fiduswriter_pandoc-4.0.3.dist-info/METADATA
fiduswriter_pandoc-4.0.3.dist-info/WHEEL
fiduswriter_pandoc-4.0.3.dist-info/top_level.txt
fiduswriter_pandoc-4.0.3.dist-info/RECORD
