Metadata-Version: 2.4
Name: fiduswriter-pandoc
Version: 4.0.3
Summary: A Fidus Writer plugin to connect to Pandoc.
Author-email: Johannes Wilm <johannes@fiduswriter.org>
License-Expression: AGPL-3.0-or-later
Project-URL: repository, https://github.com/fiduswriter/fiduswriter-pandoc
Classifier: Environment :: Web Environment
Classifier: Framework :: Django
Classifier: Framework :: Django :: 5.1
Classifier: Intended Audience :: Developers
Classifier: Operating System :: OS Independent
Classifier: Programming Language :: Python
Classifier: Programming Language :: Python :: 3
Classifier: Topic :: Internet :: WWW/HTTP
Classifier: Topic :: Internet :: WWW/HTTP :: Dynamic Content
License-File: LICENSE
Dynamic: license-file
